{
  "pageErrors": [],
  "consoleErrors": [],
  "values": {
    "actions>buy_mana_z1>tooltip2": "\n            点法力。会按你当前买得起的额度一次买满。<br>对普通人来说，这只是图个方便；对现在的你来说，这几乎就是最直接的续命手段。<br>探索度达到 20% 后解锁。\n            \n      ",
    "actions>buy_mana_challenge>tooltip2": "\n            点法力。会按你当前买得起的额度一次买满。<br>只是法力荒期间，这名商人手里总共也只剩 7500 点法力可卖。<br>在挑战里，这往往就是你离开新手镇前最关键的一笔资源。<br>探索度达到 20% 后解锁。\n            \n      ",
    "actions>buy_mana_z3>tooltip2": "\n            点法力。会按商贸城当前最划算的市价一次买满。这里的价值不只在便宜，更在于货源够多、比价也方便。\n            \n      ",
    "actions>buy_mana_z5>tooltip2": "\n            点法力。会按神界市场的报价一次买满。能不能算便宜另说，但至少在这里，你总能直接从贸易之神的秤上把货买到手。\n            \n      "
  }
}